azure/__init__.py
azure/cli/__init__.py
azure/cli/command_modules/__init__.py
azure/cli/command_modules/reservations/__init__.py
azure/cli/command_modules/reservations/_client_factory.py
azure/cli/command_modules/reservations/_exception_handler.py
azure/cli/command_modules/reservations/_help.py
azure/cli/command_modules/reservations/_params.py
azure/cli/command_modules/reservations/commands.py
azure/cli/command_modules/reservations/custom.py
opal_azure_cli_reservations-0.4.5.dist-info/METADATA
opal_azure_cli_reservations-0.4.5.dist-info/WHEEL
opal_azure_cli_reservations-0.4.5.dist-info/top_level.txt
opal_azure_cli_reservations-0.4.5.dist-info/RECORD
